CMakeLists.txt
LICENSE
MANIFEST.in
README.md
setup.py
lib/s2_py/__init__.py
lib/s2_py.egg-info/PKG-INFO
lib/s2_py.egg-info/SOURCES.txt
lib/s2_py.egg-info/dependency_links.txt
lib/s2_py.egg-info/not-zip-safe
lib/s2_py.egg-info/top_level.txt
s2geometry/CMakeLists.txt
s2geometry/doc/examples/CMakeLists.txt
s2geometry/doc/examples/point_index.cc
s2geometry/doc/examples/term_index.cc
s2geometry/doc/examples/term_index.py
s2geometry/src/python/CMakeLists.txt
s2geometry/src/python/coder.i
s2geometry/src/python/pywraps2_test.py
s2geometry/src/python/s2.i
s2geometry/src/python/s2_common.i
s2geometry/src/s2/_fp_contract_off.h
s2geometry/src/s2/encoded_s2cell_id_vector.cc
s2geometry/src/s2/encoded_s2cell_id_vector.h
s2geometry/src/s2/encoded_s2cell_id_vector_test.cc
s2geometry/src/s2/encoded_s2point_vector.cc
s2geometry/src/s2/encoded_s2point_vector.h
s2geometry/src/s2/encoded_s2point_vector_test.cc
s2geometry/src/s2/encoded_s2shape_index.cc
s2geometry/src/s2/encoded_s2shape_index.h
s2geometry/src/s2/encoded_s2shape_index_test.cc
s2geometry/src/s2/encoded_string_vector.cc
s2geometry/src/s2/encoded_string_vector.h
s2geometry/src/s2/encoded_string_vector_test.cc
s2geometry/src/s2/encoded_uint_vector.h
s2geometry/src/s2/encoded_uint_vector_test.cc
s2geometry/src/s2/id_set_lexicon.cc
s2geometry/src/s2/id_set_lexicon.h
s2geometry/src/s2/id_set_lexicon_test.cc
s2geometry/src/s2/mutable_s2shape_index.cc
s2geometry/src/s2/mutable_s2shape_index.h
s2geometry/src/s2/mutable_s2shape_index_test.cc
s2geometry/src/s2/r1interval.h
s2geometry/src/s2/r1interval_test.cc
s2geometry/src/s2/r2.h
s2geometry/src/s2/r2rect.cc
s2geometry/src/s2/r2rect.h
s2geometry/src/s2/r2rect_test.cc
s2geometry/src/s2/s1angle.cc
s2geometry/src/s2/s1angle.h
s2geometry/src/s2/s1angle_test.cc
s2geometry/src/s2/s1chord_angle.cc
s2geometry/src/s2/s1chord_angle.h
s2geometry/src/s2/s1chord_angle_test.cc
s2geometry/src/s2/s1interval.cc
s2geometry/src/s2/s1interval.h
s2geometry/src/s2/s1interval_test.cc
s2geometry/src/s2/s2boolean_operation.cc
s2geometry/src/s2/s2boolean_operation.h
s2geometry/src/s2/s2boolean_operation_test.cc
s2geometry/src/s2/s2builder.cc
