Metadata-Version: 1.0
Name: s2-py
Version: 0.11.0
Summary: pip-able S2 Geometry Bindings
Home-page: UNKNOWN
Author: Gabe Frangakis
Author-email: UNKNOWN
License: Apache
Platform: UNKNOWN
